{
  "parent": "westerosblocks:block/untinted/cube_overlay",
  "textures": {
    "down": "westerosblocks:block/plaster/smooth/light_grey/all",
    "down_ov": "westerosblocks:block/timber/white/bottom",
    "east": "westerosblocks:block/plaster/smooth/light_grey/all",
    "east_ov": "westerosblocks:block/timber/white/bressummer",
    "north": "westerosblocks:block/plaster/smooth/light_grey/all",
    "north_ov": "westerosblocks:block/timber/white/bressummer",
    "particle": "westerosblocks:block/plaster/smooth/light_grey/all",
    "south": "westerosblocks:block/plaster/smooth/light_grey/all",
    "south_ov": "westerosblocks:block/timber/white/bressummer",
    "up": "westerosblocks:block/wood/white/all",
    "up_ov": "westerosblocks:block/transparent",
    "west": "westerosblocks:block/plaster/smooth/light_grey/all",
    "west_ov": "westerosblocks:block/timber/white/bressummer"
  }
}