{
  "parent": "westerosblocks:block/untinted/half_slab",
  "textures": {
    "down": "westerosblocks:block/terrainset_reach_alt/12",
    "up": "westerosblocks:block/terrainset_reach_alt/12",
    "north": "westerosblocks:block/terrainset_reach_alt/12",
    "south": "westerosblocks:block/terrainset_reach_alt/12",
    "west": "westerosblocks:block/terrainset_reach_alt/12",
    "east": "westerosblocks:block/terrainset_reach_alt/12",
    "particle": "westerosblocks:block/terrainset_reach_alt/12"
  }
}