{
    "blockName": "timber_oak_reach_brick_close_studding",
    "blockType": "solid",
    "hardness": 2,
    "stepSound": "wood",
    "material": "wood",
    "resistance": 5,
    "creativeTab": "westeros_timber_frame_tab",
    "label": "Timber Oak Fieldstone Reach Close Studding",
    "type": "connectstate:true,toggleOnUse",
    "states": [
        {
            "textures": [
                "fieldstone/reach/all",
                "wood/oak/all",
                "fieldstone/reach/all"
            ]
        },
        {
            "textures": [
                "ashlar_smooth/reach/all_cutout",
                "wood/oak/all",
                "ashlar_smooth/reach/all_cutout"
            ]
        },
        {
            "textures": [
                "ashlar_quarter_rounded/reach/all",
                "wood/oak/all",
                "ashlar_quarter_rounded/reach/all"
            ]
        }
    ],
    "overlayTextures": [
        "timber/oak/bottom",
        "transparent",
        "timber/oak/close_studding"
    ]
}