{
  "parent": "westerosblocks:block/untinted/upper_slab",
  "textures": {
    "down": "westerosblocks:block/plaster/smooth/orange/all",
    "east": "westerosblocks:block/plaster/smooth/orange/all",
    "north": "westerosblocks:block/plaster/smooth/orange/all",
    "particle": "westerosblocks:block/plaster/smooth/orange/all",
    "south": "westerosblocks:block/plaster/smooth/orange/all",
    "up": "westerosblocks:block/plaster/smooth/orange/all",
    "west": "westerosblocks:block/plaster/smooth/orange/all"
  }
}