{
    "baseBlockName": "pink_wool",
    "variants": [
        "solid",
        "stairs",
        "slab",
        "wall",
        "fence",
        "tip",
        "carpet"
    ],
    "hardness": 1.5,
    "stepSound": "cloth",
    "material": "wood",
    "resistance": 4,
    "harvestLevel": [
        {
            "tool": "axe",
            "level": 1
        }
    ],
    "creativeTab": "westeros_cloth_fibers_tab",
    "customTags": [
        "wool-ctm"
    ],
    "altCustomTags": {
        "solid": [
            "wool-block-ctm"
        ]
    },
    "baseLabel": "Pink Wool",
    "textures": {
        "all": "wool/pink/all"
    },
    "altTextures": {
        "solid": [
            "wool/pink/block"
        ],
        "carpet": [
            "wool/pink/noctm"
        ]
    }
}